from_ipfs/__init__.py
from_ipfs/cli.py
from_ipfs/llama_cpp_patch.py
from_ipfs/main.py
from_ipfs/patcher.py
from_ipfs/transformers_patch.py
from_ipfs/utils.py
from_ipfs/config/__init__.py
from_ipfs/config/config.py
from_ipfs/config/from_ipfs_config_cmd.sh
from_ipfs/debug/__init__.py
from_ipfs/debug/cli_debug.py
from_ipfs/debug/debug_config.py
from_ipfs/debug/debug_patching.py
from_ipfs/llama_cpp/__init__.py
from_ipfs/transformers/__init__.py
from_ipfs-0.1.0.dist-info/METADATA
from_ipfs-0.1.0.dist-info/WHEEL
from_ipfs-0.1.0.dist-info/entry_points.txt
from_ipfs-0.1.0.dist-info/RECORD
