Metadata-Version: 2.4
Name: from_ipfs
Version: 0.1.0
Summary: Use IPFS URIs with Hugging Face transformers and llama.cpp Python bindings
Project-URL: Homepage, https://github.com/alexbakers/from_ipfs
Project-URL: Issues, https://github.com/alexbakers/from_ipfs/issues
Project-URL: Documentation, https://github.com/alexbakers/from_ipfs#readme
Project-URL: Repository, https://github.com/alexbakers/from_ipfs.git
Author: alexbakers
License: MIT
Keywords: decentralized,huggingface,ipfs,llama-cpp-python,models,transformers
Classifier: Development Status :: 4 - Beta
Classifier: Intended Audience :: Developers
Classifier: Intended Audience :: Science/Research
Classifier: License :: OSI Approved :: MIT License
Classifier: Programming Language :: Python :: 3
Classifier: Programming Language :: Python :: 3.8
Classifier: Programming Language :: Python :: 3.9
Classifier: Programming Language :: Python :: 3.10
Classifier: Programming Language :: Python :: 3.11
Classifier: Programming Language :: Python :: 3.12
Classifier: Topic :: Scientific/Engineering :: Artificial Intelligence
Requires-Python: >=3.8
Requires-Dist: requests>=2.25.0
Requires-Dist: tqdm>=4.65.0
Provides-Extra: all
Requires-Dist: huggingface-hub>=0.19.0; extra == 'all'
Requires-Dist: llama-cpp-python>=0.2.0; extra == 'all'
Requires-Dist: torch>=2.0.0; extra == 'all'
Requires-Dist: transformers>=4.0.0; extra == 'all'
Provides-Extra: dev
Requires-Dist: black>=23.0.0; extra == 'dev'
Requires-Dist: huggingface-hub>=0.19.0; extra == 'dev'
Requires-Dist: isort>=5.12.0; extra == 'dev'
Requires-Dist: llama-cpp-python>=0.2.0; extra == 'dev'
Requires-Dist: pytest-cov>=4.1.0; extra == 'dev'
Requires-Dist: pytest>=7.0.0; extra == 'dev'
Requires-Dist: ruff>=0.0.254; extra == 'dev'
Requires-Dist: torch>=2.0.0; extra == 'dev'
Requires-Dist: transformers>=4.0.0; extra == 'dev'
Provides-Extra: llama-cpp
Requires-Dist: llama-cpp-python>=0.2.0; extra == 'llama-cpp'
Provides-Extra: transformers
Requires-Dist: transformers>=4.0.0; extra == 'transformers'
